py_cric/__init__.py
py_cric/pycric.py
pycric-0.0.1.dist-info/METADATA
pycric-0.0.1.dist-info/WHEEL
pycric-0.0.1.dist-info/top_level.txt
pycric-0.0.1.dist-info/RECORD
