Metadata-Version: 2.1
Name: pycric
Version: 0.0.1
Summary: Tested 90%% accurate test match score prediction through your cricket knowledge
Home-page: UNKNOWN
Author: YusiferZendric (Aditya Singh)
Author-email: <mail@yusiferzendric.com>
License: UNKNOWN
Keywords: python,prediction,without machine learning,cricket,player score prediction
Platform: UNKNOWN
Classifier: Development Status :: 1 - Planning
Classifier: Intended Audience :: Developers
Classifier: Programming Language :: Python :: 3
Classifier: Operating System :: Unix
Classifier: Operating System :: MacOS :: MacOS X
Classifier: Operating System :: Microsoft :: Windows
